elegansbot/__init__.py
elegansbot/elegansbot.py
elegansbot-1.0.2.dist-info/licenses/LICENSE
elegansbot-1.0.2.dist-info/METADATA
elegansbot-1.0.2.dist-info/WHEEL
elegansbot-1.0.2.dist-info/top_level.txt
elegansbot-1.0.2.dist-info/RECORD
