Metadata-Version: 2.4
Name: ElegansBot
Version: 1.0.2
Summary: Newtonian Mechanics Model for C. elegans Locomotion
Home-page: https://github.com/TaegonChung/ElegansBot
Author: Taegon Chung
Author-email: sunny2ys@dgist.ac.kr
Classifier: Programming Language :: Python :: 3
Classifier: License :: OSI Approved :: MIT License
Classifier: Operating System :: OS Independent
License-File: LICENSE
Requires-Dist: numpy>=1.19.0
Requires-Dist: numba>=0.54.0
Requires-Dist: scipy>=1.5.0
Requires-Dist: matplotlib>=3.4.2
Dynamic: author
Dynamic: author-email
Dynamic: classifier
Dynamic: description
Dynamic: description-content-type
Dynamic: home-page
Dynamic: license-file
Dynamic: requires-dist
Dynamic: summary
